Metadata-Version: 1.0
Name: azbuka-morze
Version: 1.0
Summary: Azbuka_morze_ot_stepika
Home-page: UNKNOWN
Author: UNKNOWN
Author-email: stanislav.sipan@yandex.ru
License: UNKNOWN
Platform: UNKNOWN
